EventAnalysis/__init__.py
EventAnalysis/src/ECAKernel.py
EventAnalysis/src/ECALoop.py
EventAnalysis/src/ESKernel.py
EventAnalysis/src/ESLoop.py
EventAnalysis/src/EventAnalysis.py
EventAnalysis/src/__init__.py
EventAnalysis/src/utils.py
event_analysis-1.1.3.dist-info/LICENSE.txt
event_analysis-1.1.3.dist-info/METADATA
event_analysis-1.1.3.dist-info/WHEEL
event_analysis-1.1.3.dist-info/top_level.txt
event_analysis-1.1.3.dist-info/RECORD
