Metadata-Version: 2.1
Name: event-analysis
Version: 1.1.3
Summary: This package allows you to run Event Coincidence Analysis and Event Synchronization on your event series on the CPU and Nvidia-GPU
Home-page: https://github.com/professorcode1/Event-Analysis
Author: Raghav Kumar
Author-email: raghkum2000@gmail.com
Classifier: Development Status :: 5 - Production/Stable
Classifier: Intended Audience :: Science/Research
Classifier: License :: OSI Approved :: MIT License
Classifier: Operating System :: OS Independent
Classifier: Programming Language :: Python
Classifier: Programming Language :: Python :: 3
License-File: LICENSE.txt
Requires-Dist: numba
Requires-Dist: numpy
Requires-Dist: pandas
